metadata_py-2.0.0.dist-info/licenses/LICENSE
update_metadata/__init__.py
update_metadata/cli.py
update_metadata/core.py
metadata_py-2.0.0.dist-info/METADATA
metadata_py-2.0.0.dist-info/WHEEL
metadata_py-2.0.0.dist-info/entry_points.txt
metadata_py-2.0.0.dist-info/top_level.txt
metadata_py-2.0.0.dist-info/RECORD
